setup.py
flaticon/__init__.py
flaticon/client.py
flaticon/models.py
flaticon/utils.py
tests/__init__.py
tests/test_client.py
flaticon-1.0.2.dist-info/LICENSE
flaticon-1.0.2.dist-info/METADATA
flaticon-1.0.2.dist-info/WHEEL
flaticon-1.0.2.dist-info/top_level.txt
flaticon-1.0.2.dist-info/RECORD
